{
  "type": "minecraft:chest",
  "pools": [
    {
      "rolls": 1,
      "entries": [
        {
          "type": "minecraft:item",
          "weight": 7,
          "name": "newexp:netherite_tools",
          "functions": [
            {
              "function": "minecraft:set_count",
              "count": 1
            }
          ]
        },
        {
          "type": "minecraft:item",
          "weight": 2,
          "name": "newexp:npickaxe",
          "functions": [
            {
              "function": "minecraft:set_count",
              "count": 1
            }
          ]
        },
        {
          "type": "minecraft:item",
          "weight": 1,
          "name": "newexp:enchanted_netherite_statue",
          "functions": [
            {
              "function": "minecraft:set_count",
              "count": 1
            }
          ]
        }
      ]
    },
    {
      "rolls": 3,
      "bonus_rolls": 1,
      "entries": [
        {
          "type": "minecraft:item",
          "weight": 4,
          "name": "newexp:netherite_statue",
          "functions": [
            {
              "function": "minecraft:set_count",
              "count": {
                "min": 1,
                "max": 2
              }
            }
          ]
        },
        {
          "type": "minecraft:item",
          "weight": 4,
          "name": "newexp:netherite_amulet",
          "functions": [
            {
              "function": "minecraft:set_count",
              "count": {
                "min": 1,
                "max": 2
              }
            }
          ]
        },
        {
          "type": "minecraft:item",
          "weight": 4,
          "name": "newexp:netherite_artifact",
          "functions": [
            {
              "function": "minecraft:set_count",
              "count": {
                "min": 1,
                "max": 2
              }
            }
          ]
        },
        {
          "type": "minecraft:item",
          "weight": 3,
          "name": "newexp:raw_nererite",
          "functions": [
            {
              "function": "minecraft:set_count",
              "count": {
                "min": 2,
                "max": 4
              }
            }
          ]
        },
        {
          "type": "minecraft:item",
          "weight": 3,
          "name": "newexp:refined_nererite",
          "functions": [
            {
              "function": "minecraft:set_count",
              "count": {
                "min": 1,
                "max": 3
              }
            }
          ]
        },
        {
          "type": "minecraft:item",
          "weight": 2,
          "name": "newexp:netherite_tools",
          "functions": [
            {
              "function": "minecraft:set_count",
              "count": 1
            }
          ]
        }
      ]
    },
    {
      "rolls": 3,
      "entries": [
        {
          "type": "minecraft:item",
          "weight": 15,
          "functions": [
            {
              "function": "minecraft:set_count",
              "count": {
                "min": 1,
                "max": 2
              }
            }
          ],
          "name": "minecraft:netherite_ingot"
        },
        {
          "type": "minecraft:item",
          "weight": 10,
          "functions": [
            {
              "function": "minecraft:set_count",
              "count": {
                "min": 1,
                "max": 3
              }
            }
          ],
          "name": "minecraft:ancient_debris"
        },
        {
          "type": "minecraft:item",
          "weight": 8,
          "functions": [
            {
              "function": "minecraft:set_count",
              "count": {
                "min": 1,
                "max": 3
              }
            }
          ],
          "name": "minecraft:netherite_scrap"
        },
        {
          "type": "minecraft:item",
          "weight": 4,
          "functions": [
            {
              "function": "minecraft:set_count",
              "count": {
                "min": 2,
                "max": 6
              }
            }
          ],
          "name": "minecraft:ancient_debris"
        },
        {
          "type": "minecraft:item",
          "weight": 6,
          "functions": [
            {
              "function": "minecraft:set_damage",
              "damage": {
                "min": 0.8,
                "max": 1.0
              }
            },
            {
              "function": "minecraft:enchant_randomly"
            }
          ],
          "name": "newexp:dsword"
        },
        {
          "type": "minecraft:item",
          "weight": 6,
          "functions": [
            {
              "function": "minecraft:set_damage",
              "damage": {
                "min": 0.8,
                "max": 1.0
              }
            },
            {
              "function": "minecraft:enchant_randomly"
            }
          ],
          "name": "newexp:dchestplate"
        },
        {
          "type": "minecraft:item",
          "weight": 6,
          "functions": [
            {
              "function": "minecraft:set_damage",
              "damage": {
                "min": 0.8,
                "max": 1.0
              }
            },
            {
              "function": "minecraft:enchant_randomly"
            }
          ],
          "name": "newexp:dhelmet"
        },
        {
          "type": "minecraft:item",
          "weight": 6,
          "functions": [
            {
              "function": "minecraft:set_damage",
              "damage": {
                "min": 0.8,
                "max": 1.0
              }
            },
            {
              "function": "minecraft:enchant_randomly"
            }
          ],
          "name": "newexp:dleggings"
        },
        {
          "type": "minecraft:item",
          "weight": 6,
          "functions": [
            {
              "function": "minecraft:set_damage",
              "damage": {
                "min": 0.8,
                "max": 1.0
              }
            },
            {
              "function": "minecraft:enchant_randomly"
            }
          ],
          "name": "newexp:dboots"
        },
        {
          "type": "minecraft:item",
          "weight": 6,
          "name": "newexp:dsword"
        },
        {
          "type": "minecraft:item",
          "weight": 5,
          "name": "newexp:dchestplate"
        },
        {
          "type": "minecraft:item",
          "weight": 5,
          "name": "newexp:dhelmet"
        },
        {
          "type": "minecraft:item",
          "weight": 5,
          "name": "newexp:dboots"
        },
        {
          "type": "minecraft:item",
          "weight": 5,
          "name": "newexp:dleggings"
        },
        {
          "type": "minecraft:item",
          "weight": 5,
          "functions": [
            {
              "function": "minecraft:set_count",
              "count": {
                "min": 2.0,
                "max": 6.0,
                "type": "minecraft:uniform"
              }
            }
          ],
          "name": "minecraft:diamond"
        },
        {
          "type": "minecraft:item",
          "weight": 2,
          "functions": [
            {
              "function": "minecraft:set_count",
              "count": 1
            }
          ],
          "name": "minecraft:enchanted_golden_apple"
        }
      ]
    },
    {
      "rolls": {
        "min": 4.0,
        "max": 5.0,
        "type": "minecraft:uniform"
      },
      "entries": [
        {
          "type": "minecraft:item",
          "functions": [
            {
              "function": "minecraft:set_count",
              "count": {
                "min": 12.0,
                "max": 25.0,
                "type": "minecraft:uniform"
              }
            }
          ],
          "name": "minecraft:spectral_arrow"
        },
        {
          "type": "minecraft:item",
          "functions": [
            {
              "function": "minecraft:set_count",
              "count": {
                "min": 2.0,
                "max": 5.0,
                "type": "minecraft:uniform"
              }
            }
          ],
          "name": "minecraft:gold_block"
        },
        {
          "type": "minecraft:item",
          "functions": [
            {
              "function": "minecraft:set_count",
              "count": {
                "min": 2.0,
                "max": 5.0,
                "type": "minecraft:uniform"
              }
            }
          ],
          "name": "minecraft:iron_block"
        },
        {
          "type": "minecraft:item",
          "functions": [
            {
              "function": "minecraft:set_count",
              "count": {
                "min": 3.0,
                "max": 9.0,
                "type": "minecraft:uniform"
              }
            }
          ],
          "name": "minecraft:gold_ingot"
        },
        {
          "type": "minecraft:item",
          "functions": [
            {
              "function": "minecraft:set_count",
              "count": {
                "min": 3.0,
                "max": 9.0,
                "type": "minecraft:uniform"
              }
            }
          ],
          "name": "minecraft:iron_ingot"
        },
        {
          "type": "minecraft:item",
          "functions": [
            {
              "function": "minecraft:set_count",
              "count": {
                "min": 3.0,
                "max": 5.0,
                "type": "minecraft:uniform"
              }
            }
          ],
          "name": "minecraft:crying_obsidian"
        },
        {
          "type": "minecraft:item",
          "functions": [
            {
              "function": "minecraft:set_count",
              "count": {
                "min": 18.0,
                "max": 46.0,
                "type": "minecraft:uniform"
              }
            }
          ],
          "name": "minecraft:quartz"
        },
        {
          "type": "minecraft:item",
          "functions": [
            {
              "function": "minecraft:set_count",
              "count": {
                "min": 15.0,
                "max": 25.0,
                "type": "minecraft:uniform"
              }
            }
          ],
          "name": "minecraft:gilded_blackstone"
        },
        {
          "type": "minecraft:item",
          "functions": [
            {
              "function": "minecraft:set_count",
              "count": {
                "min": 3.0,
                "max": 5.0,
                "type": "minecraft:uniform"
              }
            }
          ],
          "name": "minecraft:blaze_rod"
        }
      ]
    }
  ]
}